Metadata-Version: 2.4
Name: openai-websearch-mcp-fastmcp
Version: 0.4.3
Summary: using openai websearch as mcp server
Project-URL: Homepage, https://github.com/fastmcp-me/openai-websearch-mcp#readme
Project-URL: Repository, https://github.com/fastmcp-me/openai-websearch-mcp.git
Project-URL: Issues, https://github.com/fastmcp-me/openai-websearch-mcp/issues
License-File: LICENSE
Requires-Python: >=3.10
Requires-Dist: mcp==1.13.1
Requires-Dist: openai==1.66.2
Requires-Dist: pydantic-extra-types==2.10.3
Requires-Dist: pydantic<3.0.0,>=2.11.0
Requires-Dist: typer==0.15.2
Requires-Dist: tzdata==2025.1
